<annotation>
	<folder></folder>
	<filename>02fe3eea41166a1d3eb75307a12c4a63_png_jpg.rf.7e55bbdec642c5dc0a873fc685611677.jpg</filename>
	<path>02fe3eea41166a1d3eb75307a12c4a63_png_jpg.rf.7e55bbdec642c5dc0a873fc685611677.jpg</path>
	<source>
		<database>roboflow.ai</database>
	</source>
	<size>
		<width>1024</width>
		<height>1024</height>
		<depth>3</depth>
	</size>
	<segmented>0</segmented>
	<object>
		<name>Nodule</name>
		<pose>Unspecified</pose>
		<truncated>0</truncated>
		<difficult>0</difficult>
		<occluded>0</occluded>
		<bndbox>
			<xmin>698</xmin>
			<xmax>751</xmax>
			<ymin>296</ymin>
			<ymax>337</ymax>
		</bndbox>
	</object>
	<object>
		<name>Nodule</name>
		<pose>Unspecified</pose>
		<truncated>0</truncated>
		<difficult>0</difficult>
		<occluded>0</occluded>
		<bndbox>
			<xmin>750</xmin>
			<xmax>783</xmax>
			<ymin>197</ymin>
			<ymax>227</ymax>
		</bndbox>
	</object>
	<object>
		<name>Nodule</name>
		<pose>Unspecified</pose>
		<truncated>0</truncated>
		<difficult>0</difficult>
		<occluded>0</occluded>
		<bndbox>
			<xmin>757</xmin>
			<xmax>809</xmax>
			<ymin>242</ymin>
			<ymax>282</ymax>
		</bndbox>
	</object>
	<object>
		<name>Nodule</name>
		<pose>Unspecified</pose>
		<truncated>0</truncated>
		<difficult>0</difficult>
		<occluded>0</occluded>
		<bndbox>
			<xmin>699</xmin>
			<xmax>728</xmax>
			<ymin>371</ymin>
			<ymax>394</ymax>
		</bndbox>
	</object>
</annotation>
