<annotation>
	<folder></folder>
	<filename>1812172c7ad3771c05d1238bb3066217_png_jpg.rf.bc71c1f6e64d1ccbcd62643e2290851a.jpg</filename>
	<path>1812172c7ad3771c05d1238bb3066217_png_jpg.rf.bc71c1f6e64d1ccbcd62643e2290851a.jpg</path>
	<source>
		<database>roboflow.ai</database>
	</source>
	<size>
		<width>1024</width>
		<height>1024</height>
		<depth>3</depth>
	</size>
	<segmented>0</segmented>
	<object>
		<name>Nodule</name>
		<pose>Unspecified</pose>
		<truncated>0</truncated>
		<difficult>0</difficult>
		<occluded>0</occluded>
		<bndbox>
			<xmin>289</xmin>
			<xmax>319</xmax>
			<ymin>542</ymin>
			<ymax>558</ymax>
		</bndbox>
	</object>
	<object>
		<name>Nodule</name>
		<pose>Unspecified</pose>
		<truncated>0</truncated>
		<difficult>0</difficult>
		<occluded>0</occluded>
		<bndbox>
			<xmin>302</xmin>
			<xmax>332</xmax>
			<ymin>358</ymin>
			<ymax>386</ymax>
		</bndbox>
	</object>
	<object>
		<name>Nodule</name>
		<pose>Unspecified</pose>
		<truncated>0</truncated>
		<difficult>0</difficult>
		<occluded>0</occluded>
		<bndbox>
			<xmin>281</xmin>
			<xmax>313</xmax>
			<ymin>444</ymin>
			<ymax>479</ymax>
		</bndbox>
	</object>
	<object>
		<name>Nodule</name>
		<pose>Unspecified</pose>
		<truncated>0</truncated>
		<difficult>0</difficult>
		<occluded>0</occluded>
		<bndbox>
			<xmin>832</xmin>
			<xmax>864</xmax>
			<ymin>510</ymin>
			<ymax>551</ymax>
		</bndbox>
	</object>
	<object>
		<name>Nodule</name>
		<pose>Unspecified</pose>
		<truncated>0</truncated>
		<difficult>0</difficult>
		<occluded>0</occluded>
		<bndbox>
			<xmin>290</xmin>
			<xmax>329</xmax>
			<ymin>206</ymin>
			<ymax>231</ymax>
		</bndbox>
	</object>
	<object>
		<name>Nodule</name>
		<pose>Unspecified</pose>
		<truncated>0</truncated>
		<difficult>0</difficult>
		<occluded>0</occluded>
		<bndbox>
			<xmin>902</xmin>
			<xmax>923</xmax>
			<ymin>749</ymin>
			<ymax>774</ymax>
		</bndbox>
	</object>
	<object>
		<name>Nodule</name>
		<pose>Unspecified</pose>
		<truncated>0</truncated>
		<difficult>0</difficult>
		<occluded>0</occluded>
		<bndbox>
			<xmin>830</xmin>
			<xmax>859</xmax>
			<ymin>610</ymin>
			<ymax>633</ymax>
		</bndbox>
	</object>
	<object>
		<name>Nodule</name>
		<pose>Unspecified</pose>
		<truncated>0</truncated>
		<difficult>0</difficult>
		<occluded>0</occluded>
		<bndbox>
			<xmin>209</xmin>
			<xmax>235</xmax>
			<ymin>711</ymin>
			<ymax>735</ymax>
		</bndbox>
	</object>
	<object>
		<name>Nodule</name>
		<pose>Unspecified</pose>
		<truncated>0</truncated>
		<difficult>0</difficult>
		<occluded>0</occluded>
		<bndbox>
			<xmin>783</xmin>
			<xmax>815</xmax>
			<ymin>557</ymin>
			<ymax>593</ymax>
		</bndbox>
	</object>
	<object>
		<name>Nodule</name>
		<pose>Unspecified</pose>
		<truncated>0</truncated>
		<difficult>0</difficult>
		<occluded>0</occluded>
		<bndbox>
			<xmin>202</xmin>
			<xmax>243</xmax>
			<ymin>519</ymin>
			<ymax>562</ymax>
		</bndbox>
	</object>
	<object>
		<name>Nodule</name>
		<pose>Unspecified</pose>
		<truncated>0</truncated>
		<difficult>0</difficult>
		<occluded>0</occluded>
		<bndbox>
			<xmin>333</xmin>
			<xmax>359</xmax>
			<ymin>620</ymin>
			<ymax>651</ymax>
		</bndbox>
	</object>
</annotation>
