<annotation>
	<folder></folder>
	<filename>7cc9b48563e197c84ec4ee8d30d5b3ce_png_jpg.rf.a6173872210a54f6d25be75fd1eb2f1a.jpg</filename>
	<path>7cc9b48563e197c84ec4ee8d30d5b3ce_png_jpg.rf.a6173872210a54f6d25be75fd1eb2f1a.jpg</path>
	<source>
		<database>roboflow.ai</database>
	</source>
	<size>
		<width>1024</width>
		<height>1024</height>
		<depth>3</depth>
	</size>
	<segmented>0</segmented>
	<object>
		<name>Nodule</name>
		<pose>Unspecified</pose>
		<truncated>0</truncated>
		<difficult>0</difficult>
		<occluded>0</occluded>
		<bndbox>
			<xmin>317</xmin>
			<xmax>435</xmax>
			<ymin>386</ymin>
			<ymax>480</ymax>
		</bndbox>
	</object>
	<object>
		<name>Nodule</name>
		<pose>Unspecified</pose>
		<truncated>0</truncated>
		<difficult>0</difficult>
		<occluded>0</occluded>
		<bndbox>
			<xmin>642</xmin>
			<xmax>887</xmax>
			<ymin>503</ymin>
			<ymax>719</ymax>
		</bndbox>
	</object>
</annotation>
