<annotation>
	<folder></folder>
	<filename>n1124_png_jpg.rf.938027ddd27cf9bb8c06997d658051f6.jpg</filename>
	<path>n1124_png_jpg.rf.938027ddd27cf9bb8c06997d658051f6.jpg</path>
	<source>
		<database>roboflow.ai</database>
	</source>
	<size>
		<width>1024</width>
		<height>1024</height>
		<depth>3</depth>
	</size>
	<segmented>0</segmented>
	<object>
		<name>Nodule</name>
		<pose>Unspecified</pose>
		<truncated>0</truncated>
		<difficult>0</difficult>
		<occluded>0</occluded>
		<bndbox>
			<xmin>787</xmin>
			<xmax>831</xmax>
			<ymin>744</ymin>
			<ymax>797</ymax>
		</bndbox>
	</object>
	<object>
		<name>Nodule</name>
		<pose>Unspecified</pose>
		<truncated>0</truncated>
		<difficult>0</difficult>
		<occluded>0</occluded>
		<bndbox>
			<xmin>728</xmin>
			<xmax>765</xmax>
			<ymin>569</ymin>
			<ymax>607</ymax>
		</bndbox>
	</object>
</annotation>
